milearn/__init__.py
milearn/preprocessing.py
milearn/data/__init__.py
milearn/data/mnist.py
milearn/network/__init__.py
milearn/network/classifier.py
milearn/network/regressor.py
milearn/network/module/__init__.py
milearn/network/module/attention.py
milearn/network/module/base.py
milearn/network/module/classic.py
milearn/network/module/dynamic.py
milearn/network/module/hopt.py
milearn/network/module/mlp.py
milearn/network/module/utils.py
milearn/wrapper/__init__.py
milearn/wrapper/base.py
mikit_learn-1.0.0.dist-info/METADATA
mikit_learn-1.0.0.dist-info/WHEEL
mikit_learn-1.0.0.dist-info/top_level.txt
mikit_learn-1.0.0.dist-info/RECORD
